README.md
setup.cfg
setup.py
smart_fflags_client.egg-info/PKG-INFO
smart_fflags_client.egg-info/SOURCES.txt
smart_fflags_client.egg-info/dependency_links.txt
smart_fflags_client.egg-info/requires.txt
smart_fflags_client.egg-info/top_level.txt
smartflags/__init__.py